{
  "hero": {
    "typedLines": [
      "المنتدى الشبابي للفكر والمشاركة المدنية",
      "المبادرة الشبابية الأولى في ولاية الطارف",
      "نسعى لتمكين الشباب فكريًا ومدنيًا",
      "نزاهة... بك ومعك"
    ],
    "subtitle": "نزاهة... بك ومعك",
    "btnText": "اقرأ المزيد"
  },
  "aboutText": "المنتدى الشبابي للفكر والمشاركة المدنية \"نزاهة\" هو مبادرة شبابية مستقلة، انطلقت من ولاية الطارف، تهدف إلى تمكين الشباب فكرياً ومدنياً من خلال تقديم حلول علمية ومنهجية لمواجهة التحديات الفكرية والاجتماعية. يركز المنتدى على تنمية التفكير النقدي، تعزيز الوعي المدني، وتأطير الفئة العمرية (14–30 سنة) عبر برامج تكوينية، ورش عمل، وندوات فكرية. يعمل المنتدى وفق ركائز أساسية: النزاهة، الشفافية، المشاركة المجتمعية المسؤولة.",
  "boardMembers": [
    {
      "name": "نزيه عبدالله بومهني",
      "title": "مؤسس ورئيس المنتدى",
      "description": "ناشط سياسي وشبابي وجمعوي، باحث في العلاقات الدولية والشأن الخليجي والعربي. من مواليد 19 يوليو بولاية عنابة.",
      "facebook": "https://www.facebook.com/nazihboumahni",
      "instagram": "https://www.instagram.com/nazihboumahni"
    },
    {
      "name": "صلاح الدين بن قسمية",
      "title": "أمين السر المكلف بديوان الرئاسة",
      "description": "ناشط شبابي من مواليد ولاية الجلفة الجزائرية.",
      "facebook": "https://www.facebook.com/nazaha.36",
      "instagram": ""
    }
  ],
  "extras": [
    {
      "title": "النظام الداخلي",
      "description": "اطلع على النظام الأساسي للمنتدى، الهيكل التنظيمي، وشروط العضوية.",
      "icon": "file-pdf",
      "modalId": "bylawModal"
    },
    {
      "title": "معلومات الدفع",
      "description": "تعرف على رسوم الاشتراك وطرق الدفع المعتمدة.",
      "icon": "credit-card",
      "modalId": "paymentModal"
    }
  ],
  "social": {
    "facebook": "https://www.facebook.com/nazaha.36",
    "instagram": "https://www.instagram.com/nazaha.36",
    "twitter": "https://twitter.com/nazaha_36",
    "email": "mailto:nazahaa36.inf@gmail.com"
  },
  "mapEmbedUrl": "https://www.google.com/maps/embed?pb=!1m18!1m12!1m3!1d102146.40243171124!2d8.24354785!3d36.75673895!2m3!1f0!2f0!3f0!3m2!1i1024!2i768!4f13.1!3m3!1m2!1s0x12f000371302821d%3A0x673105777176166a!2sEl%20Taref!5e0!3m2!1sen!2sdz!4v1710000000000",
  "footerText": "© 2026 المنتدى الشبابي للفكر والمشاركة المدنية – نزاهة | جميع الحقوق محفوظة",
  "newsEvents": []
}
